{
  "name": "swig",
  "config-opts": [
    "--without-pcre",
    "--without-tcl",
    "--without-perl5",
    "--without-octave",
    "--without-scilab",
    "--without-java",
    "--without-javascript",
    "--without-gcj",
    "--without-android",
    "--without-guile",
    "--without-mzscheme",
    "--without-ruby",
    "--without-php5",
    "--without-php",
    "--without-ocaml",
    "--without-pike",
    "--without-chiken",
    "--without-csharp",
    "--without-lua",
    "--without-allegrocl",
    "--without-clisp",
    "--without-r",
    "--without-go",
    "--without-d"
  ],
  "sources": [
    {
      "type": "archive",
      "url": "http://prdownloads.sourceforge.net/swig/swig-3.0.11.tar.gz",
      "sha256": "d9031d531d7418829a54d0d51c4ed9007016b213657ec70be44031951810566e"
    }
  ],
  "modules": [
    {
      "name": "libxml2",
      "config-opts": [
        "--without-python"
      ],
      "sources": [
        {
          "type": "archive",
          "url": "http://xmlsoft.org/sources/libxml2-2.9.4.tar.gz",
          "sha256": "ffb911191e509b966deb55de705387f14156e1a56b21824357cdf0053233633c"
        }
      ]
    },
    {
      "name": "libxslt",
      "config-opts": [
        "--without-python"
      ],
      "sources": [
        {
          "type": "archive",
          "url": "http://xmlsoft.org/sources/libxslt-1.1.29.tar.gz",
          "sha256": "b5976e3857837e7617b29f2249ebb5eeac34e249208d31f1fbf7a6ba7a4090ce"
        }
      ]
    }
  ]
}